sensor901/__init__.py
sensor901/data.py
sensor901/parser.py
sensor901/simulator.py
sensor901-0.0.7.dist-info/METADATA
sensor901-0.0.7.dist-info/WHEEL
sensor901-0.0.7.dist-info/RECORD
